setup.py
tokenapiv4/main.py
tokenapiv4.egg-info/PKG-INFO
tokenapiv4.egg-info/SOURCES.txt
tokenapiv4.egg-info/dependency_links.txt
tokenapiv4.egg-info/top_level.txt