Metadata-Version: 2.1
Name: tokenapiv4
Version: 1.0
Summary: Discord selfbot api manager
Author: helper
License: MIT
Keywords: style
Classifier: Development Status :: 5 - Production/Stable
